securetrading/__init__.py
securetrading/abstractstobject.py
securetrading/api.py
securetrading/config.py
securetrading/converter.py
securetrading/exceptions.py
securetrading/httpclient.py
securetrading/phrasebook.py
securetrading/requestobject.py
securetrading/responseobject.py
securetrading/util.py
securetrading/data/errormessages.json
securetrading/data/phrasebook.json
securetrading/test/__init__.py
securetrading/test/abstract_test.py
securetrading/test/abstract_test_stobjects.py
securetrading/test/badcacert.pem
securetrading/test/module_test_api.py
securetrading/test/test_api.py
securetrading/test/test_codeformat.py
securetrading/test/test_config.py
securetrading/test/test_converter.py
securetrading/test/test_exceptions.py
securetrading/test/test_httpclient.py
securetrading/test/test_phrasebook.py
securetrading/test/test_requestobject.py
securetrading/test/test_responseobject.py
securetrading/test/test_util.py
securetrading/test/testcacert.pem
securetrading-1.0.24.dist-info/licenses/LICENSE
securetrading-1.0.24.dist-info/METADATA
securetrading-1.0.24.dist-info/WHEEL
securetrading-1.0.24.dist-info/top_level.txt
securetrading-1.0.24.dist-info/RECORD
