Metadata-Version: 2.4
Name: securetrading
Version: 1.0.24
Summary: Python API to connect to Secure Trading
Home-page: https://github.com/SecureTrading/st-python-api
Author: Secure Trading
Author-email: devapi@trustpayments.com
License: MIT
Keywords: securetrading api python trustpayments
Classifier: Development Status :: 3 - Alpha
Classifier: Intended Audience :: Developers
Classifier: Topic :: Software Development :: Libraries :: Python Modules
Classifier: License :: OSI Approved :: MIT License
Classifier: Programming Language :: Python :: 2.7
Classifier: Programming Language :: Python :: 3.3
Classifier: Programming Language :: Python :: 3.5
Classifier: Programming Language :: Python :: 3.6
Classifier: Programming Language :: Python :: 3.7
Classifier: Programming Language :: Python :: 3.8
Classifier: Programming Language :: Python :: 3.9
Classifier: Programming Language :: Python :: 3.10
Classifier: Programming Language :: Python :: 3.11
Classifier: Programming Language :: Python :: 3.12
Classifier: Operating System :: OS Independent
License-File: LICENSE
Requires-Dist: requests>=2.9.0
Provides-Extra: test
Requires-Dist: pep8; extra == "test"
Requires-Dist: six; extra == "test"
Dynamic: author
Dynamic: author-email
Dynamic: classifier
Dynamic: description
Dynamic: home-page
Dynamic: keywords
Dynamic: license
Dynamic: license-file
Dynamic: provides-extra
Dynamic: requires-dist
Dynamic: summary
